shorten_text/__init__.py
shorten_text/shorten.py
shorten_text/test.py
shorten_text-1.0.4.dist-info/METADATA
shorten_text-1.0.4.dist-info/WHEEL
shorten_text-1.0.4.dist-info/top_level.txt
shorten_text-1.0.4.dist-info/RECORD
