Metadata-Version: 2.1
Name: shorten-text
Version: 1.0.4
Summary: shorten the text
Home-page: https://github.com/projecta-auth/Pypi_test_publish.git
Author: Krishna
License: MIT
